{
  "formatVersion": "1.1",
  "component": {
    "group": "com.distrimind.bouncycastle",
    "module": "pg",
    "version": "1.69-DMRECOMPILE",
    "attributes": {
      "org.gradle.status": "release"
    }
  },
  "createdBy": {
    "gradle": {
      "version": "7.2"
    }
  },
  "variants": [
    {
      "name": "apiElements",
      "attributes": {
        "org.gradle.category": "library",
        "org.gradle.dependency.bundling": "external",
        "org.gradle.jvm.version": 8,
        "org.gradle.libraryelements": "jar",
        "org.gradle.usage": "java-api"
      },
      "files": [
        {
          "name": "pg-1.69-DMRECOMPILE.jar",
          "url": "pg-1.69-DMRECOMPILE.jar",
          "size": 416198,
          "sha512": "cc1f9288894dcaba13b035671c1d2e5d2056c04fa48e13c271b1168b350ed05d784b2ebccf0de31994dc72b8c1dc77f3cca4caeac570800ab1a4af65afd9f5e2",
          "sha256": "3b0104a51580e99551a5696ba8981765568e2eeb1abc75cfa815cf8fc61fc064",
          "sha1": "a375d919a48da05dfa7b333ac94b0621e6996ea1",
          "md5": "2b5620dc14b69c212f47f04b290793ab"
        }
      ]
    },
    {
      "name": "runtimeElements",
      "attributes": {
        "org.gradle.category": "library",
        "org.gradle.dependency.bundling": "external",
        "org.gradle.jvm.version": 8,
        "org.gradle.libraryelements": "jar",
        "org.gradle.usage": "java-runtime"
      },
      "dependencies": [
        {
          "group": "com.distrimind.bouncycastle",
          "module": "core",
          "version": {
            "requires": "1.69-DMRECOMPILE"
          }
        },
        {
          "group": "com.distrimind.bouncycastle",
          "module": "prov",
          "version": {
            "requires": "1.69-DMRECOMPILE"
          }
        }
      ],
      "files": [
        {
          "name": "pg-1.69-DMRECOMPILE.jar",
          "url": "pg-1.69-DMRECOMPILE.jar",
          "size": 416198,
          "sha512": "cc1f9288894dcaba13b035671c1d2e5d2056c04fa48e13c271b1168b350ed05d784b2ebccf0de31994dc72b8c1dc77f3cca4caeac570800ab1a4af65afd9f5e2",
          "sha256": "3b0104a51580e99551a5696ba8981765568e2eeb1abc75cfa815cf8fc61fc064",
          "sha1": "a375d919a48da05dfa7b333ac94b0621e6996ea1",
          "md5": "2b5620dc14b69c212f47f04b290793ab"
        }
      ]
    }
  ]
}
